MANIFEST.in
README.rst
setup.py
vincent/__init__.py
vincent/_compat.py
vincent/axes.py
vincent/charts.py
vincent/colors.py
vincent/core.py
vincent/data.py
vincent/factories.py
vincent/ipynb.py
vincent/legends.py
vincent/marks.py
vincent/properties.py
vincent/scales.py
vincent/transforms.py
vincent/values.py
vincent/vega_template.html
vincent/visualization.py
vincent.egg-info/PKG-INFO
vincent.egg-info/SOURCES.txt
vincent.egg-info/dependency_links.txt
vincent.egg-info/requires.txt
vincent.egg-info/top_level.txt
vincent.egg-info/zip-safe