Metadata-Version: 1.1
Name: vincent
Version: 0.3.0
Summary: A Python to Vega translator
Home-page: https://github.com/wrobstory/vincent
Author: Rob Story
Author-email: wrobstory@gmail.com
License: MIT License
Keywords: data visualization
Platform: UNKNOWN
Classifier: Development Status :: 4 - Beta
Classifier: Programming Language :: Python :: 2.7
Classifier: Programming Language :: Python :: 3.2
Classifier: Programming Language :: Python :: 3.3
Classifier: License :: OSI Approved :: MIT License
